trie_search/__init__.py
trie_search/record_trie.py
trie_search/trie.py
trie_search-0.3.0.dist-info/DESCRIPTION.rst
trie_search-0.3.0.dist-info/METADATA
trie_search-0.3.0.dist-info/RECORD
trie_search-0.3.0.dist-info/WHEEL
trie_search-0.3.0.dist-info/metadata.json
trie_search-0.3.0.dist-info/top_level.txt
