Metadata-Version: 2.0
Name: trie-search
Version: 0.3.0
Summary: Trie-search is a package for text pattern search using marisa-trie
Home-page: https://github.com/nkmrtty/trie-search
Author: Tatsuya Nakamura
Author-email: nkmrtty.com@gmail.com
License: MIT
Platform: UNKNOWN
Classifier: Intended Audience :: Science/Research
Classifier: Programming Language :: Python :: 2
Classifier: Programming Language :: Python :: 2.7
Classifier: Programming Language :: Python :: 3
Classifier: Programming Language :: Python :: 3.5
Classifier: License :: OSI Approved :: MIT License
Classifier: Topic :: Text Processing
Requires-Dist: marisa-trie (==0.7.4)
